{
  "launcher": {
    "version": "1.2.3",
    "url": "https://www.dropbox.com/scl/fi/i7kalgbzqpkl8mzk545th/FBISoft.exe?rlkey=5m7izm0aysdvzual08gds4j9q&dl=1",
    "changelog": "Cloudzy сервер, фикс автообновления, SSL, цены"
  },
  "scripts": {
    "parser": {
      "name": "📱 Osint Parser",
      "description": "Сбор информации для удобной и продуктивной работы.",
      "version": "2.4.0",
      "status": "stable",
      "module": "osint_parser",
      "url": "https://www.dropbox.com/scl/fi/yqc1nx2b3j1af8xbvwh29/osint_parser.exe?rlkey=yy2q3wzm8v6x8fhoi98oovojw&dl=1",
      "changelog": "CHD (Credit Header Data) integration, provider names removed, API limits for CHD"
    },
    "auto_motion": {
      "name": "🤖 Auto Motion",
      "description": "Автоматизация действий.",
      "version": "1.1.1",
      "status": "stable",
      "module": "Auto_Motion",
      "url": "https://www.dropbox.com/scl/fi/gfv6stk2ry58crx4kl4lg/Auto_Motion.exe?rlkey=v2rpa0gu3ef1r1zftyhpuyste&st=eu876bxt&dl=1",
      "changelog": "Исправление WebInspector API"
    }
  },
  "sig": "7837da2deed36d0d27fae7cc1f860f9a21e1848afa782b37e4cf1a8d991de587"
}
