{
  "launcher": {
    "version": "1.2.3",
    "url": "https://www.dropbox.com/scl/fi/i7kalgbzqpkl8mzk545th/FBISoft.exe?rlkey=5m7izm0aysdvzual08gds4j9q&dl=1",
    "changelog": "Cloudzy сервер, фикс автообновления, SSL, цены"
  },
  "scripts": {
    "parser": {
      "name": "📱 Osint Parser",
      "description": "Сбор информации для удобной и продуктивной работы.",
      "version": "2.2.5",
      "status": "stable",
      "module": "osint_parser",
      "url": "https://www.dropbox.com/scl/fi/6eikln1n77tia177wq88r/osint_parser.exe?rlkey=bezqu0xmn8va1ziyhu53sxfkb&dl=1",
      "changelog": "Rate limit detection and retry, age column, Caller ID data in Bank API"
    },
    "auto_motion": {
      "name": "🤖 Auto Motion",
      "description": "Автоматизация действий.",
      "version": "1.1.1",
      "status": "stable",
      "module": "Auto_Motion",
      "url": "https://www.dropbox.com/scl/fi/gfv6stk2ry58crx4kl4lg/Auto_Motion.exe?rlkey=v2rpa0gu3ef1r1zftyhpuyste&st=eu876bxt&dl=1",
      "changelog": "Исправление WebInspector API"
    }
  },
  "sig": "bc728767adf98e4e2122e33b39abddc50b262633c5c230f23925d4d86cc0f0bf"
}
